dguard_vad/__init__.py
dguard_vad/cli.py
dguard_vad/dguard_vad.py
dguard_vad/frame_queue.py
dguard_vad/pickable_session.py
dguard_vad/utils.py
dguard_vad-0.1.1.dist-info/LICENSE
dguard_vad-0.1.1.dist-info/METADATA
dguard_vad-0.1.1.dist-info/WHEEL
dguard_vad-0.1.1.dist-info/entry_points.txt
dguard_vad-0.1.1.dist-info/top_level.txt
dguard_vad-0.1.1.dist-info/RECORD
